byted_overpass_lab_ocrx_fusion_general/__init__.py
byted_overpass_lab_ocrx_fusion_general-0.0.1.dist-info/METADATA
byted_overpass_lab_ocrx_fusion_general-0.0.1.dist-info/WHEEL
byted_overpass_lab_ocrx_fusion_general-0.0.1.dist-info/top_level.txt
byted_overpass_lab_ocrx_fusion_general-0.0.1.dist-info/RECORD
